<?xml version="1.0" encoding="utf-8" ?><dwsync><file name="#header.png" server="ftp.dotslash.dk/stage/" local="3515605771" remote="319783739159761288" Dst="-1" /><file name="#teaser.png" server="ftp.dotslash.dk/stage/" local="3515747163" remote="319783739159761288" Dst="-1" /><file name="01_after_effects.png" server="ftp.dotslash.dk/stage/" local="3515602579" remote="319783739159761288" Dst="-1" /><file name="02_tv_intro.mp4" server="ftp.dotslash.dk/stage/" local="3515608485" remote="319783739159761288" Dst="-1" /><file name="02_tv_intro.webm" server="ftp.dotslash.dk/stage/" local="3515608601" remote="319783739159761288" Dst="-1" /><file name="case.txt" server="ftp.dotslash.dk/stage/" local="3511708238" remote="319783739159761288" Dst="-1" /><file name="case.txt" server="ftp.dotslash.dk" local="3518464451" remote="319783739162322388" Dst="-1" /><file name="02_tv_intro.mp4" server="ftp.dotslash.dk" local="3516850948" remote="319783739161024288" Dst="-1" /><file name="02_tv_intro.gif" server="ftp.dotslash.dk" local="3516690661" remote="319783739161080208" Dst="-1" /><file name="02_tv_intro.mobile.mp4" server="ftp.dotslash.dk" local="3516850948" remote="319783739161080208" Dst="-1" /><file name="02_tv_intro.videostill.jpg" server="ftp.dotslash.dk" local="3517221616" remote="319783739161080208" Dst="-1" /><file name="#header.png" server="dotslash.dk/www/" local="3515605771" remote="319783739165996908" Dst="-1" /><file name="#teaser.png" server="dotslash.dk/www/" local="3515747163" remote="319783739165996908" Dst="-1" /><file name="01_after_effects.png" server="dotslash.dk/www/" local="3515602579" remote="319783739165996908" Dst="-1" /><file name="02_tv_intro.gif" server="dotslash.dk/www/" local="3516690661" remote="319783739165996908" Dst="-1" /><file name="02_tv_intro.mobile.mp4" server="dotslash.dk/www/" local="3516850948" remote="319783739165996908" Dst="-1" /><file name="02_tv_intro.mp4" server="dotslash.dk/www/" local="3516850948" remote="319783739165996908" Dst="-1" /><file name="02_tv_intro.videostill.jpg" server="dotslash.dk/www/" local="3517221616" remote="319783739165996968" Dst="-1" /><file name="02_tv_intro.webm" server="dotslash.dk/www/" local="3515608601" remote="319783739165996968" Dst="-1" /><file name="case.txt" server="dotslash.dk/www/" local="3518464451" remote="319783739165996968" Dst="-1" /></dwsync>