<?xml version="1.0" encoding="utf-8" ?><dwsync><file name="case.php" server="ftp.dotslash.dk/stage/" local="3515392070" remote="319783739159761348" Dst="-1" /><file name="default.php" server="ftp.dotslash.dk/stage/" local="3515392115" remote="319783739159761348" Dst="-1" /><file name="error.php" server="ftp.dotslash.dk/stage/" local="3515392057" remote="319783739159761348" Dst="-1" /><file name="home.php" server="ftp.dotslash.dk/stage/" local="3515392115" remote="319783739159761348" Dst="-1" /><file name="portfolio.php" server="ftp.dotslash.dk/stage/" local="3515392115" remote="319783739159761348" Dst="-1" /><file name="site.php" server="ftp.dotslash.dk/stage/" local="3515392115" remote="319783739159761348" Dst="-1" /><file name="case.php" server="ftp.dotslash.dk" local="3517830168" remote="319783739161710388" Dst="-1" /><file name="default.php" server="ftp.dotslash.dk" local="3515392115" remote="319783739160296788" Dst="-1" /><file name="error.php" server="ftp.dotslash.dk" local="3515392057" remote="319783739160296788" Dst="-1" /><file name="home.php" server="ftp.dotslash.dk" local="3515392115" remote="319783739160296788" Dst="-1" /><file name="portfolio.php" server="ftp.dotslash.dk" local="3515392115" remote="319783739160296788" Dst="-1" /><file name="site.php" server="ftp.dotslash.dk" local="3515392115" remote="319783739160296788" Dst="-1" /><file name="case.php" server="dotslash.dk/www/" local="3517830168" remote="319783739165997628" Dst="-1" /><file name="default.php" server="dotslash.dk/www/" local="3515392115" remote="319783739165997628" Dst="-1" /><file name="error.php" server="dotslash.dk/www/" local="3515392057" remote="319783739165997628" Dst="-1" /><file name="home.php" server="dotslash.dk/www/" local="3515392115" remote="319783739165997628" Dst="-1" /><file name="portfolio.php" server="dotslash.dk/www/" local="3515392115" remote="319783739165997628" Dst="-1" /><file name="site.php" server="dotslash.dk/www/" local="3515392115" remote="319783739165997628" Dst="-1" /></dwsync>